README.md
setup.cfg
setup.py
augmentation_lib/__init__.py
augmentation_lib/augmentation.py
augmentation_lib/constants.py
augmentation_lib/utils.py
augmentation_lib.egg-info/PKG-INFO
augmentation_lib.egg-info/SOURCES.txt
augmentation_lib.egg-info/dependency_links.txt
augmentation_lib.egg-info/requires.txt
augmentation_lib.egg-info/top_level.txt